geoAssembler/__init__.py
geoAssembler/__main__.py
geoAssembler/calibrants.py
geoAssembler/defaults.py
geoAssembler/geometry.py
geoAssembler/io_utils.py
geoAssembler/main.py
geoAssembler/cells/LiTiO2.D
geoAssembler/icons/agipd_geometry.png
geoAssembler/icons/circle.png
geoAssembler/icons/clear-all.png
geoAssembler/icons/clear.png
geoAssembler/icons/file.png
geoAssembler/icons/gtk-cancel.png
geoAssembler/icons/gtk-ok.png
geoAssembler/icons/log.png
geoAssembler/icons/main_icon_128x128.png
geoAssembler/icons/main_icon_32x32.png
geoAssembler/icons/main_icon_64x64.png
geoAssembler/icons/open.png
geoAssembler/icons/quads.png
geoAssembler/icons/save.png
geoAssembler/icons/shapes.png
geoAssembler/icons/square.png
geoAssembler/icons/system-run.png
geoAssembler/nb/__init__.py
geoAssembler/nb/notebook.py
geoAssembler/nb/tabs.py
geoAssembler/nb/template.py
geoAssembler/nb/templates/geoAssembler.tmpl
geoAssembler/optimiser/__init__.py
geoAssembler/optimiser/centre.py
geoAssembler/optimiser/utility.py
geoAssembler/qt/__init__.py
geoAssembler/qt/app.py
geoAssembler/qt/objects.py
geoAssembler/qt/subwidgets.py
geoAssembler/qt/utils.py
geoAssembler/qt/editor/__init__.py
geoAssembler/qt/editor/fit_object.ui
geoAssembler/qt/editor/geometry_editor.ui
geoAssembler/qt/editor/load_detector.ui
geoAssembler/qt/editor/run_data.ui
geoAssembler/tests/__init__.py
geoAssembler/tests/conftest.py
geoAssembler/tests/data_agipd.npz
geoAssembler/tests/data_lpd.npz
geoAssembler/tests/test.geom
geoAssembler/tests/test_centre_optimiser.py
geoAssembler/tests/test_geometry.py
geoAssembler/tests/test_main.py
geoAssembler/tests/test_notebook.py
geoAssembler/tests/test_panelview.py
geoAssembler/tests/utils.py
geoAssembler-0.6.0.dist-info/METADATA
geoAssembler-0.6.0.dist-info/WHEEL
geoAssembler-0.6.0.dist-info/entry_points.txt
geoAssembler-0.6.0.dist-info/top_level.txt
geoAssembler-0.6.0.dist-info/RECORD
