Metadata-Version: 2.1
Name: geoAssembler
Version: 0.6.0
Summary: Tool to Calibrate Detector Geometry Based on Power Diffraction Pattern
Home-page: https://git.xfel.eu/gitlab/dataAnalysis/geoAssembler
Author: European XFEL GmbH
Author-email: cas-support@xfel.eu
Maintainer: Martin Bergemann
License: BSD-3-Clause
Platform: UNKNOWN
Classifier: Development Status :: 3 - Alpha
Classifier: Environment :: Console
Classifier: Intended Audience :: Developers
Classifier: Intended Audience :: Science/Research
Classifier: License :: OSI Approved :: BSD License
Classifier: Operating System :: POSIX :: Linux
Classifier: Programming Language :: Python :: 3
Classifier: Topic :: Scientific/Engineering :: Information Analysis
Classifier: Topic :: Scientific/Engineering :: Physics
Requires-Python: >=3.4
Requires-Dist: cfelpyutils
Requires-Dist: EXtra-data
Requires-Dist: EXtra-geom
Requires-Dist: ipywidgets
Requires-Dist: matplotlib
Requires-Dist: numpy
Requires-Dist: pyFai
Requires-Dist: PyQt5 (<=6.0.0,>=5.13.2)
Requires-Dist: PyQt5-sip (<=13.0.0,>=12.7.0)
Requires-Dist: pyqtgraph
Requires-Dist: scipy
Requires-Dist: xarray (>=0.14.1)
Provides-Extra: docs
Requires-Dist: ipython ; extra == 'docs'
Requires-Dist: nbsphinx ; extra == 'docs'
Requires-Dist: sphinx ; extra == 'docs'
Provides-Extra: test
Requires-Dist: pytest ; extra == 'test'
Requires-Dist: testpath ; extra == 'test'
